aiinbx/__init__.py
aiinbx/_base_client.py
aiinbx/_client.py
aiinbx/_compat.py
aiinbx/_constants.py
aiinbx/_exceptions.py
aiinbx/_files.py
aiinbx/_models.py
aiinbx/_qs.py
aiinbx/_resource.py
aiinbx/_response.py
aiinbx/_streaming.py
aiinbx/_types.py
aiinbx/_version.py
aiinbx/py.typed
aiinbx/_utils/__init__.py
aiinbx/_utils/_compat.py
aiinbx/_utils/_datetime_parse.py
aiinbx/_utils/_json.py
aiinbx/_utils/_logs.py
aiinbx/_utils/_proxy.py
aiinbx/_utils/_reflection.py
aiinbx/_utils/_resources_proxy.py
aiinbx/_utils/_streams.py
aiinbx/_utils/_sync.py
aiinbx/_utils/_transform.py
aiinbx/_utils/_typing.py
aiinbx/_utils/_utils.py
aiinbx/lib/.keep
aiinbx/resources/__init__.py
aiinbx/resources/domains.py
aiinbx/resources/emails.py
aiinbx/resources/meta.py
aiinbx/resources/threads.py
aiinbx/resources/webhooks.py
aiinbx/types/__init__.py
aiinbx/types/domain_create_params.py
aiinbx/types/domain_create_response.py
aiinbx/types/domain_delete_response.py
aiinbx/types/domain_list_response.py
aiinbx/types/domain_retrieve_response.py
aiinbx/types/domain_verify_response.py
aiinbx/types/email_reply_params.py
aiinbx/types/email_reply_response.py
aiinbx/types/email_retrieve_response.py
aiinbx/types/email_send_params.py
aiinbx/types/email_send_response.py
aiinbx/types/inbound_email_received_webhook_event.py
aiinbx/types/meta_webhooks_schema_response.py
aiinbx/types/outbound_email_bounced_webhook_event.py
aiinbx/types/outbound_email_clicked_webhook_event.py
aiinbx/types/outbound_email_complained_webhook_event.py
aiinbx/types/outbound_email_delivered_webhook_event.py
aiinbx/types/outbound_email_opened_webhook_event.py
aiinbx/types/outbound_email_rejected_webhook_event.py
aiinbx/types/thread_forward_params.py
aiinbx/types/thread_forward_response.py
aiinbx/types/thread_retrieve_response.py
aiinbx/types/thread_search_params.py
aiinbx/types/thread_search_response.py
aiinbx/types/unwrap_webhook_event.py
aiinbx-0.361.0.dist-info/METADATA
aiinbx-0.361.0.dist-info/WHEEL
aiinbx-0.361.0.dist-info/licenses/LICENSE
aiinbx-0.361.0.dist-info/RECORD
